LICENSE.txt
README.md
setup.py
Merovingian/Merovingian.py
Merovingian.egg-info/PKG-INFO
Merovingian.egg-info/SOURCES.txt
Merovingian.egg-info/dependency_links.txt
Merovingian.egg-info/top_level.txt