Metadata-Version: 1.0
Name: Merovingian
Version: 0.1.0
Summary: DESCRIPTION ENCOMPASSES
Home-page: UNKNOWN
Author: pleasefeedme
Author-email: myfakeemail@gmail.com
License: Python. Free to use no attribution required.
Platform: UNKNOWN
